heyjude/__init__.py
heyjude/api.py
py_heyjude-0.1.2.dist-info/LICENSE
py_heyjude-0.1.2.dist-info/METADATA
py_heyjude-0.1.2.dist-info/WHEEL
py_heyjude-0.1.2.dist-info/top_level.txt
py_heyjude-0.1.2.dist-info/RECORD
