Metadata-Version: 2.1
Name: py-heyjude
Version: 0.1.2
Summary: A Python wrapper for the HeyJude API
Home-page: https://github.com/evil-toast-nom-nom/py-heyjude
Author: Evil Toast
License: UNKNOWN
Platform: UNKNOWN
Classifier: Programming Language :: Python :: 3
Classifier: License :: OSI Approved :: MIT License
Classifier: Operating System :: OS Independent
Requires-Python: >=3.6
License-File: LICENSE
Requires-Dist: requests
